{
 "MSFT": {
  "peak_pnl_pct": 1.5
 },
 "QQQ": {
  "peak_pnl_pct": -0.8
 },
 "SMH": {
  "peak_pnl_pct": 0.5
 },
 "META": {
  "peak_pnl_pct": 0.3
 },
 "SOXX": {
  "peak_pnl_pct": 4.5
 },
 "AMAT": {
  "peak_pnl_pct": 13.2
 },
 "AVGO": {
  "peak_pnl_pct": 1.3
 },
 "BLK": {
  "peak_pnl_pct": 1.3
 },
 "TNA": {
  "peak_pnl_pct": 1.4
 },
 "IGV": {
  "peak_pnl_pct": 0.0
 },
 "NVDL": {
  "peak_pnl_pct": -0.2
 },
 "SOXL": {
  "peak_pnl_pct": 3.5
 },
 "AMZN": {
  "peak_pnl_pct": 0.0
 },
 "SQQQ": {
  "peak_pnl_pct": 4.8
 },
 "ETH-USD": {
  "peak_pnl_pct": -0.0
 }
}