{
 "updated": "2026-07-22 04:01",
 "candidates": [
  {
   "symbol": "C",
   "score": 5,
   "ratio": 0.5,
   "max": 10,
   "price": 132.79,
   "reasons": [
    "RSI 44 과매도권 접근",
    "PER 10(저평가)",
    "PBR 1.2",
    "그레이엄 기준 충족"
   ]
  },
  {
   "symbol": "COF",
   "score": 5,
   "ratio": 0.5,
   "max": 10,
   "price": 206.12,
   "reasons": [
    "고점 대비 -20% 조정",
    "PER 9(저평가)",
    "PBR 1.2",
    "그레이엄 기준 충족"
   ]
  },
  {
   "symbol": "NFLX",
   "score": 4,
   "ratio": 0.4,
   "max": 10,
   "price": 67.69,
   "reasons": [
    "52주고점 대비 -38%",
    "RSI 29 과매도",
    "PER 18"
   ]
  },
  {
   "symbol": "TFC",
   "score": 4,
   "ratio": 0.4,
   "max": 10,
   "price": 51.29,
   "reasons": [
    "PER 10(저평가)",
    "PBR 1.1",
    "그레이엄 기준 충족"
   ]
  },
  {
   "symbol": "DHR",
   "score": 4,
   "ratio": 0.4,
   "max": 10,
   "price": 177.86,
   "reasons": [
    "52주고점 대비 -26%",
    "RSI 37 과매도권 접근",
    "PER 19"
   ]
  }
 ]
}